{
	"ProjectName": "front-end",
	"ProjectPath": "C:\\Users\\skalra\\OneDrive - WatchGuard Technologies Inc\\Documents\\VS code prjcts\\Eootm\\front-end",
	"InitializationTime": "",
	"LastConfigurationTime": "",
	"LastNPMInstallTime": "",
	"FrontendLastBuildTime": "",
	"LastPublishTime": "",
	"BackendLastSyncTime": "",
	"BackendLastBuildTime": "",
	"BackendLastPushTime": "",
	"BackendProjectID": "",
	"BackendProjectName": "",
	"BackendProjectConsoleUrl": "",
	"BackendProjectCreationTime": "",
	"BackendProjectLastUpdatedTime": "",
	"Framework": "angular"
}